pollination/annual_energy_use/__init__.py
pollination/annual_energy_use/entry.py
pollination_annual_energy_use-0.5.11.dist-info/LICENSE
pollination_annual_energy_use-0.5.11.dist-info/METADATA
pollination_annual_energy_use-0.5.11.dist-info/WHEEL
pollination_annual_energy_use-0.5.11.dist-info/top_level.txt
pollination_annual_energy_use-0.5.11.dist-info/RECORD
